robot_control/__init__.py
robot_control/__int__.py
robot_control/controller.py
robot_control/exceptions.py
robot_control/kinematics.py
robot_control/parallel_joints_solver.py
robot_control/robot_wrapper.py
robot_control/state_machine.py
robot_control/utils.py
robot_control/bin/__init__.py
robot_control/bin/fftai_dds_bridge
robot_control/bin/fftai_dds_bridge_wrapper.py
robot_control/pydds/__init__.py
robot_control/pydds/libpydds.so
fourier_utils-0.1.0.dist-info/METADATA
fourier_utils-0.1.0.dist-info/WHEEL
fourier_utils-0.1.0.dist-info/entry_points.txt
fourier_utils-0.1.0.dist-info/top_level.txt
fourier_utils-0.1.0.dist-info/RECORD
