Metadata-Version: 2.1
Name: fourier_utils
Version: 0.1.0
Classifier: Programming Language :: Python :: 3
Requires-Python: >=3.11
Requires-Dist: numpy==1.26.4
Requires-Dist: omegaconf==2.3.0
Requires-Dist: pin-pink==3.0.0
Requires-Dist: meshcat==0.3.2
Requires-Dist: loguru==0.7.2
